{"nodes": [{"id": "d_proyectos_judiscribe_backend_app_schemas_segmento_py", "label": "segmento.py", "file_type": "code", "source_file": "D:\\Proyectos\\Judiscribe\\backend\\app\\schemas\\segmento.py", "source_location": "L1"}, {"id": "schemas_segmento_segmentocreate", "label": "SegmentoCreate", "file_type": "code", "source_file": "D:\\Proyectos\\Judiscribe\\backend\\app\\schemas\\segmento.py", "source_location": "L10"}, {"id": "basemodel", "label": "BaseModel", "file_type": "code", "source_file": "", "source_location": ""}, {"id": "schemas_segmento_segmentoupdate", "label": "SegmentoUpdate", "file_type": "code", "source_file": "D:\\Proyectos\\Judiscribe\\backend\\app\\schemas\\segmento.py", "source_location": "L23"}, {"id": "schemas_segmento_segmentoresponse", "label": "SegmentoResponse", "file_type": "code", "source_file": "D:\\Proyectos\\Judiscribe\\backend\\app\\schemas\\segmento.py", "source_location": "L28"}, {"id": "schemas_segmento_batchdecision", "label": "BatchDecision", "file_type": "code", "source_file": "D:\\Proyectos\\Judiscribe\\backend\\app\\schemas\\segmento.py", "source_location": "L50"}, {"id": "schemas_segmento_batchupdaterequest", "label": "BatchUpdateRequest", "file_type": "code", "source_file": "D:\\Proyectos\\Judiscribe\\backend\\app\\schemas\\segmento.py", "source_location": "L55"}, {"id": "schemas_segmento_batchupdateresponse", "label": "BatchUpdateResponse", "file_type": "code", "source_file": "D:\\Proyectos\\Judiscribe\\backend\\app\\schemas\\segmento.py", "source_location": "L59"}, {"id": "schemas_segmento_rationale_1", "label": "Pydantic schemas para Segmento.", "file_type": "rationale", "source_file": "D:\\Proyectos\\Judiscribe\\backend\\app\\schemas\\segmento.py", "source_location": "L1"}], "edges": [{"source": "d_proyectos_judiscribe_backend_app_schemas_segmento_py", "target": "uuid", "relation": "imports", "context": "import", "confidence": "EXTRACTED", "source_file": "D:\\Proyectos\\Judiscribe\\backend\\app\\schemas\\segmento.py", "source_location": "L4", "weight": 1.0}, {"source": "d_proyectos_judiscribe_backend_app_schemas_segmento_py", "target": "typing", "relation": "imports_from", "context": "import", "confidence": "EXTRACTED", "source_file": "D:\\Proyectos\\Judiscribe\\backend\\app\\schemas\\segmento.py", "source_location": "L5", "weight": 1.0}, {"source": "d_proyectos_judiscribe_backend_app_schemas_segmento_py", "target": "pydantic", "relation": "imports_from", "context": "import", "confidence": "EXTRACTED", "source_file": "D:\\Proyectos\\Judiscribe\\backend\\app\\schemas\\segmento.py", "source_location": "L7", "weight": 1.0}, {"source": "d_proyectos_judiscribe_backend_app_schemas_segmento_py", "target": "schemas_segmento_segmentocreate", "relation": "contains", "confidence": "EXTRACTED", "source_file": "D:\\Proyectos\\Judiscribe\\backend\\app\\schemas\\segmento.py", "source_location": "L10", "weight": 1.0}, {"source": "schemas_segmento_segmentocreate", "target": "basemodel", "relation": "inherits", "confidence": "EXTRACTED", "source_file": "D:\\Proyectos\\Judiscribe\\backend\\app\\schemas\\segmento.py", "source_location": "L10", "weight": 1.0}, {"source": "d_proyectos_judiscribe_backend_app_schemas_segmento_py", "target": "schemas_segmento_segmentoupdate", "relation": "contains", "confidence": "EXTRACTED", "source_file": "D:\\Proyectos\\Judiscribe\\backend\\app\\schemas\\segmento.py", "source_location": "L23", "weight": 1.0}, {"source": "schemas_segmento_segmentoupdate", "target": "basemodel", "relation": "inherits", "confidence": "EXTRACTED", "source_file": "D:\\Proyectos\\Judiscribe\\backend\\app\\schemas\\segmento.py", "source_location": "L23", "weight": 1.0}, {"source": "d_proyectos_judiscribe_backend_app_schemas_segmento_py", "target": "schemas_segmento_segmentoresponse", "relation": "contains", "confidence": "EXTRACTED", "source_file": "D:\\Proyectos\\Judiscribe\\backend\\app\\schemas\\segmento.py", "source_location": "L28", "weight": 1.0}, {"source": "schemas_segmento_segmentoresponse", "target": "basemodel", "relation": "inherits", "confidence": "EXTRACTED", "source_file": "D:\\Proyectos\\Judiscribe\\backend\\app\\schemas\\segmento.py", "source_location": "L28", "weight": 1.0}, {"source": "d_proyectos_judiscribe_backend_app_schemas_segmento_py", "target": "schemas_segmento_batchdecision", "relation": "contains", "confidence": "EXTRACTED", "source_file": "D:\\Proyectos\\Judiscribe\\backend\\app\\schemas\\segmento.py", "source_location": "L50", "weight": 1.0}, {"source": "schemas_segmento_batchdecision", "target": "basemodel", "relation": "inherits", "confidence": "EXTRACTED", "source_file": "D:\\Proyectos\\Judiscribe\\backend\\app\\schemas\\segmento.py", "source_location": "L50", "weight": 1.0}, {"source": "d_proyectos_judiscribe_backend_app_schemas_segmento_py", "target": "schemas_segmento_batchupdaterequest", "relation": "contains", "confidence": "EXTRACTED", "source_file": "D:\\Proyectos\\Judiscribe\\backend\\app\\schemas\\segmento.py", "source_location": "L55", "weight": 1.0}, {"source": "schemas_segmento_batchupdaterequest", "target": "basemodel", "relation": "inherits", "confidence": "EXTRACTED", "source_file": "D:\\Proyectos\\Judiscribe\\backend\\app\\schemas\\segmento.py", "source_location": "L55", "weight": 1.0}, {"source": "d_proyectos_judiscribe_backend_app_schemas_segmento_py", "target": "schemas_segmento_batchupdateresponse", "relation": "contains", "confidence": "EXTRACTED", "source_file": "D:\\Proyectos\\Judiscribe\\backend\\app\\schemas\\segmento.py", "source_location": "L59", "weight": 1.0}, {"source": "schemas_segmento_batchupdateresponse", "target": "basemodel", "relation": "inherits", "confidence": "EXTRACTED", "source_file": "D:\\Proyectos\\Judiscribe\\backend\\app\\schemas\\segmento.py", "source_location": "L59", "weight": 1.0}, {"source": "schemas_segmento_rationale_1", "target": "d_proyectos_judiscribe_backend_app_schemas_segmento_py", "relation": "rationale_for", "confidence": "EXTRACTED", "source_file": "D:\\Proyectos\\Judiscribe\\backend\\app\\schemas\\segmento.py", "source_location": "L1", "weight": 1.0}], "raw_calls": []}