{"nodes": [{"id": "d_proyectos_judiscribe_frontend_src_app_transcribir_page_tsx", "label": "page.tsx", "file_type": "code", "source_file": "D:\\Proyectos\\Judiscribe\\frontend\\src\\app\\transcribir\\page.tsx", "source_location": "L1"}, {"id": "transcribir_page_uploadphase", "label": "UploadPhase", "file_type": "code", "source_file": "D:\\Proyectos\\Judiscribe\\frontend\\src\\app\\transcribir\\page.tsx", "source_location": "L26"}, {"id": "transcribir_page_editandodata", "label": "EditandoData", "file_type": "code", "source_file": "D:\\Proyectos\\Judiscribe\\frontend\\src\\app\\transcribir\\page.tsx", "source_location": "L28"}, {"id": "transcribir_page_uploadresult", "label": "UploadResult", "file_type": "code", "source_file": "D:\\Proyectos\\Judiscribe\\frontend\\src\\app\\transcribir\\page.tsx", "source_location": "L33"}, {"id": "transcribir_page_valid_exts", "label": "VALID_EXTS", "file_type": "code", "source_file": "D:\\Proyectos\\Judiscribe\\frontend\\src\\app\\transcribir\\page.tsx", "source_location": "L43"}, {"id": "transcribir_page_fmtbytes", "label": "fmtBytes()", "file_type": "code", "source_file": "D:\\Proyectos\\Judiscribe\\frontend\\src\\app\\transcribir\\page.tsx", "source_location": "L45"}, {"id": "transcribir_page_transcribirpage", "label": "TranscribirPage()", "file_type": "code", "source_file": "D:\\Proyectos\\Judiscribe\\frontend\\src\\app\\transcribir\\page.tsx", "source_location": "L51"}], "edges": [{"source": "d_proyectos_judiscribe_frontend_src_app_transcribir_page_tsx", "target": "react", "relation": "imports_from", "context": "import", "confidence": "EXTRACTED", "source_file": "D:\\Proyectos\\Judiscribe\\frontend\\src\\app\\transcribir\\page.tsx", "source_location": "L6", "weight": 1.0}, {"source": "d_proyectos_judiscribe_frontend_src_app_transcribir_page_tsx", "target": "navigation", "relation": "imports_from", "context": "import", "confidence": "EXTRACTED", "source_file": "D:\\Proyectos\\Judiscribe\\frontend\\src\\app\\transcribir\\page.tsx", "source_location": "L7", "weight": 1.0}, {"source": "d_proyectos_judiscribe_frontend_src_app_transcribir_page_tsx", "target": "d_proyectos_judiscribe_frontend_src_lib_api_ts", "relation": "imports_from", "context": "import", "confidence": "EXTRACTED", "source_file": "D:\\Proyectos\\Judiscribe\\frontend\\src\\app\\transcribir\\page.tsx", "source_location": "L8", "weight": 1.0}, {"source": "d_proyectos_judiscribe_frontend_src_app_transcribir_page_tsx", "target": "d_proyectos_judiscribe_frontend_src_components_auth_authguard_tsx", "relation": "imports_from", "context": "import", "confidence": "EXTRACTED", "source_file": "D:\\Proyectos\\Judiscribe\\frontend\\src\\app\\transcribir\\page.tsx", "source_location": "L9", "weight": 1.0}, {"source": "d_proyectos_judiscribe_frontend_src_app_transcribir_page_tsx", "target": "auth_authguard_authguard", "relation": "imports", "context": "import", "confidence": "EXTRACTED", "source_file": "D:\\Proyectos\\Judiscribe\\frontend\\src\\app\\transcribir\\page.tsx", "source_location": "L9", "weight": 1.0}, {"source": "d_proyectos_judiscribe_frontend_src_app_transcribir_page_tsx", "target": "d_proyectos_judiscribe_frontend_src_stores_authstore_ts", "relation": "imports_from", "context": "import", "confidence": "EXTRACTED", "source_file": "D:\\Proyectos\\Judiscribe\\frontend\\src\\app\\transcribir\\page.tsx", "source_location": "L10", "weight": 1.0}, {"source": "d_proyectos_judiscribe_frontend_src_app_transcribir_page_tsx", "target": "stores_authstore_useauthstore", "relation": "imports", "context": "import", "confidence": "EXTRACTED", "source_file": "D:\\Proyectos\\Judiscribe\\frontend\\src\\app\\transcribir\\page.tsx", "source_location": "L10", "weight": 1.0}, {"source": "d_proyectos_judiscribe_frontend_src_app_transcribir_page_tsx", "target": "d_proyectos_judiscribe_frontend_src_components_audio_audioeditorpre_tsx", "relation": "imports_from", "context": "import", "confidence": "EXTRACTED", "source_file": "D:\\Proyectos\\Judiscribe\\frontend\\src\\app\\transcribir\\page.tsx", "source_location": "L11", "weight": 1.0}, {"source": "d_proyectos_judiscribe_frontend_src_app_transcribir_page_tsx", "target": "audio_audioeditorpre_procesarresult", "relation": "imports", "context": "import", "confidence": "EXTRACTED", "source_file": "D:\\Proyectos\\Judiscribe\\frontend\\src\\app\\transcribir\\page.tsx", "source_location": "L11", "weight": 1.0}, {"source": "d_proyectos_judiscribe_frontend_src_app_transcribir_page_tsx", "target": "framer_motion", "relation": "imports_from", "context": "import", "confidence": "EXTRACTED", "source_file": "D:\\Proyectos\\Judiscribe\\frontend\\src\\app\\transcribir\\page.tsx", "source_location": "L12", "weight": 1.0}, {"source": "d_proyectos_judiscribe_frontend_src_app_transcribir_page_tsx", "target": "lucide_react", "relation": "imports_from", "context": "import", "confidence": "EXTRACTED", "source_file": "D:\\Proyectos\\Judiscribe\\frontend\\src\\app\\transcribir\\page.tsx", "source_location": "L13", "weight": 1.0}, {"source": "d_proyectos_judiscribe_frontend_src_app_transcribir_page_tsx", "target": "transcribir_page_uploadphase", "relation": "contains", "confidence": "EXTRACTED", "source_file": "D:\\Proyectos\\Judiscribe\\frontend\\src\\app\\transcribir\\page.tsx", "source_location": "L26", "weight": 1.0}, {"source": "d_proyectos_judiscribe_frontend_src_app_transcribir_page_tsx", "target": "transcribir_page_editandodata", "relation": "contains", "confidence": "EXTRACTED", "source_file": "D:\\Proyectos\\Judiscribe\\frontend\\src\\app\\transcribir\\page.tsx", "source_location": "L28", "weight": 1.0}, {"source": "d_proyectos_judiscribe_frontend_src_app_transcribir_page_tsx", "target": "transcribir_page_uploadresult", "relation": "contains", "confidence": "EXTRACTED", "source_file": "D:\\Proyectos\\Judiscribe\\frontend\\src\\app\\transcribir\\page.tsx", "source_location": "L33", "weight": 1.0}, {"source": "d_proyectos_judiscribe_frontend_src_app_transcribir_page_tsx", "target": "transcribir_page_valid_exts", "relation": "contains", "confidence": "EXTRACTED", "source_file": "D:\\Proyectos\\Judiscribe\\frontend\\src\\app\\transcribir\\page.tsx", "source_location": "L43", "weight": 1.0}, {"source": "d_proyectos_judiscribe_frontend_src_app_transcribir_page_tsx", "target": "transcribir_page_fmtbytes", "relation": "contains", "confidence": "EXTRACTED", "source_file": "D:\\Proyectos\\Judiscribe\\frontend\\src\\app\\transcribir\\page.tsx", "source_location": "L45", "weight": 1.0}, {"source": "d_proyectos_judiscribe_frontend_src_app_transcribir_page_tsx", "target": "transcribir_page_transcribirpage", "relation": "contains", "confidence": "EXTRACTED", "source_file": "D:\\Proyectos\\Judiscribe\\frontend\\src\\app\\transcribir\\page.tsx", "source_location": "L51", "weight": 1.0}, {"source": "transcribir_page_transcribirpage", "target": "transcribir_page_fmtbytes", "relation": "calls", "context": "call", "confidence": "EXTRACTED", "source_file": "D:\\Proyectos\\Judiscribe\\frontend\\src\\app\\transcribir\\page.tsx", "source_location": "L193", "weight": 1.0}], "raw_calls": [{"caller_nid": "transcribir_page_fmtbytes", "callee": "toFixed", "is_member_call": true, "source_file": "D:\\Proyectos\\Judiscribe\\frontend\\src\\app\\transcribir\\page.tsx", "source_location": "L47"}, {"caller_nid": "transcribir_page_fmtbytes", "callee": "toFixed", "is_member_call": true, "source_file": "D:\\Proyectos\\Judiscribe\\frontend\\src\\app\\transcribir\\page.tsx", "source_location": "L48"}, {"caller_nid": "transcribir_page_transcribirpage", "callee": "useRouter", "is_member_call": false, "source_file": "D:\\Proyectos\\Judiscribe\\frontend\\src\\app\\transcribir\\page.tsx", "source_location": "L52"}, {"caller_nid": "transcribir_page_transcribirpage", "callee": "useAuthStore", "is_member_call": false, "source_file": "D:\\Proyectos\\Judiscribe\\frontend\\src\\app\\transcribir\\page.tsx", "source_location": "L53"}, {"caller_nid": "transcribir_page_transcribirpage", "callee": "useEffect", "is_member_call": false, "source_file": "D:\\Proyectos\\Judiscribe\\frontend\\src\\app\\transcribir\\page.tsx", "source_location": "L55"}, {"caller_nid": "transcribir_page_transcribirpage", "callee": "useRef", "is_member_call": false, "source_file": "D:\\Proyectos\\Judiscribe\\frontend\\src\\app\\transcribir\\page.tsx", "source_location": "L59"}, {"caller_nid": "transcribir_page_transcribirpage", "callee": "useState", "is_member_call": false, "source_file": "D:\\Proyectos\\Judiscribe\\frontend\\src\\app\\transcribir\\page.tsx", "source_location": "L60"}, {"caller_nid": "transcribir_page_transcribirpage", "callee": "useState", "is_member_call": false, "source_file": "D:\\Proyectos\\Judiscribe\\frontend\\src\\app\\transcribir\\page.tsx", "source_location": "L61"}, {"caller_nid": "transcribir_page_transcribirpage", "callee": "useState", "is_member_call": false, "source_file": "D:\\Proyectos\\Judiscribe\\frontend\\src\\app\\transcribir\\page.tsx", "source_location": "L62"}, {"caller_nid": "transcribir_page_transcribirpage", "callee": "useState", "is_member_call": false, "source_file": "D:\\Proyectos\\Judiscribe\\frontend\\src\\app\\transcribir\\page.tsx", "source_location": "L63"}, {"caller_nid": "transcribir_page_transcribirpage", "callee": "useState", "is_member_call": false, "source_file": "D:\\Proyectos\\Judiscribe\\frontend\\src\\app\\transcribir\\page.tsx", "source_location": "L64"}, {"caller_nid": "transcribir_page_transcribirpage", "callee": "useState", "is_member_call": false, "source_file": "D:\\Proyectos\\Judiscribe\\frontend\\src\\app\\transcribir\\page.tsx", "source_location": "L65"}, {"caller_nid": "transcribir_page_transcribirpage", "callee": "useState", "is_member_call": false, "source_file": "D:\\Proyectos\\Judiscribe\\frontend\\src\\app\\transcribir\\page.tsx", "source_location": "L66"}, {"caller_nid": "transcribir_page_transcribirpage", "callee": "useState", "is_member_call": false, "source_file": "D:\\Proyectos\\Judiscribe\\frontend\\src\\app\\transcribir\\page.tsx", "source_location": "L68"}, {"caller_nid": "transcribir_page_transcribirpage", "callee": "useState", "is_member_call": false, "source_file": "D:\\Proyectos\\Judiscribe\\frontend\\src\\app\\transcribir\\page.tsx", "source_location": "L69"}, {"caller_nid": "transcribir_page_transcribirpage", "callee": "useState", "is_member_call": false, "source_file": "D:\\Proyectos\\Judiscribe\\frontend\\src\\app\\transcribir\\page.tsx", "source_location": "L70"}, {"caller_nid": "transcribir_page_transcribirpage", "callee": "useState", "is_member_call": false, "source_file": "D:\\Proyectos\\Judiscribe\\frontend\\src\\app\\transcribir\\page.tsx", "source_location": "L71"}, {"caller_nid": "transcribir_page_transcribirpage", "callee": "useCallback", "is_member_call": false, "source_file": "D:\\Proyectos\\Judiscribe\\frontend\\src\\app\\transcribir\\page.tsx", "source_location": "L73"}, {"caller_nid": "transcribir_page_transcribirpage", "callee": "useCallback", "is_member_call": false, "source_file": "D:\\Proyectos\\Judiscribe\\frontend\\src\\app\\transcribir\\page.tsx", "source_location": "L118"}]}